bard_webapi/__init__.py
bard_webapi/client.py
bard_webapi/consts.py
bard_webapi/types.py
bard_webapi/utils.py
bard_webapi-0.2.4.dist-info/LICENSE
bard_webapi-0.2.4.dist-info/METADATA
bard_webapi-0.2.4.dist-info/WHEEL
bard_webapi-0.2.4.dist-info/top_level.txt
bard_webapi-0.2.4.dist-info/RECORD
