Metadata-Version: 2.1
Name: bard-webapi
Version: 0.2.4
Summary: Reverse-engineered async API for Google Bard inspired by Gemini
Author: UZQueen
License: MIT License
Project-URL: Repository, https://github.com/HanaokaYuzu/Bard-API
Project-URL: Issues, https://github.com/HanaokaYuzu/Bard-API/issues
Keywords: API,async,Bard,Google Bard,Google,Gemini,LLM
Classifier: Development Status :: 4 - Beta
Classifier: Intended Audience :: Developers
Classifier: License :: OSI Approved :: MIT License
Classifier: Programming Language :: Python :: 3
Classifier: Programming Language :: Python :: 3.11
Requires-Python: >=3.7
License-File: LICENSE
Requires-Dist: httpx >=0.25.2
Requires-Dist: pydantic >=2.5.3
Requires-Dist: loguru >=0.7.2
